Workbook

Sheet Dashboard
A1: SALES & PROFIT ANALYTICS DASHBOARD
A2: Ringkasan kinerja penjualan, keuntungan, kategori produk, dan wilayah
A4: TOTAL SALES | D4: TOTAL PROFIT | G4: TOTAL ORDERS | J4: AVG. PROFIT MARGIN | M4: UNITS SOLD
A5: =SUM(Data!$W$2:$W$1001) | D5: =SUM(Data!$X$2:$X$1001) | G5: =SUMPRODUCT((Data!$A$2:$A$1001<>"")/COUNTIF(Data!$A$2:$A$1001,Data!$A$2:$A$1001)) | J5: =AVERAGE(Data!$Y$2:$Y$1001)/100 | M5: =SUM(Data!$S$2:$S$1001)
A9: Monthly Performance | E9: Sales by Category | I9: Sales by Region | M9: Order Status
A10: Month-Year | B10: Sales | C10: Profit | E10: Category | F10: Sales | G10: Profit | I10: Region | J10: Sales | K10: Profit | M10: Status | N10: Orders
A11: May-23 | B11: =SUMIF(Data!$G$2:$G$1001,A11,Data!$W$2:$W$1001) | C11: =SUMIF(Data!$G$2:$G$1001,A11,Data!$X$2:$X$1001) | E11: Accessories | F11: =SUMIF(Data!$L$2:$L$1001,E11,Data!$W$2:$W$1001) | G11: =SUMIF(Data!$L$2:$L$1001,E11,Data!$X$2:$X$1001) | I11: Central | J11: =SUMIF(Data!$O$2:$O$1001,I11,Data!$W$2:$W$1001) | K11: =SUMIF(Data!$O$2:$O$1001,I11,Data!$X$2:$X$1001) | M11: Completed | N11: =COUNTIF(Data!$AB$2:$AB$1001,M11)
A12: Jun-23 | B12: =SUMIF(Data!$G$2:$G$1001,A12,Data!$W$2:$W$1001) | C12: =SUMIF(Data!$G$2:$G$1001,A12,Data!$X$2:$X$1001) | E12: Appliances | F12: =SUMIF(Data!$L$2:$L$1001,E12,Data!$W$2:$W$1001) | G12: =SUMIF(Data!$L$2:$L$1001,E12,Data!$X$2:$X$1001) | I12: North | J12: =SUMIF(Data!$O$2:$O$1001,I12,Data!$W$2:$W$1001) | K12: =SUMIF(Data!$O$2:$O$1001,I12,Data!$X$2:$X$1001) | M12: Pending | N12: =COUNTIF(Data!$AB$2:$AB$1001,M12)
A13: Jul-23 | B13: =SUMIF(Data!$G$2:$G$1001,A13,Data!$W$2:$W$1001) | C13: =SUMIF(Data!$G$2:$G$1001,A13,Data!$X$2:$X$1001) | E13: Electronics | F13: =SUMIF(Data!$L$2:$L$1001,E13,Data!$W$2:$W$1001) | G13: =SUMIF(Data!$L$2:$L$1001,E13,Data!$X$2:$X$1001) | I13: South | J13: =SUMIF(Data!$O$2:$O$1001,I13,Data!$W$2:$W$1001) | K13: =SUMIF(Data!$O$2:$O$1001,I13,Data!$X$2:$X$1001) | M13: Shipped | N13: =COUNTIF(Data!$AB$2:$AB$1001,M13)
A14: Aug-23 | B14: =SUMIF(Data!$G$2:$G$1001,A14,Data!$W$2:$W$1001) | C14: =SUMIF(Data!$G$2:$G$1001,A14,Data!$X$2:$X$1001) | E14: Furniture | F14: =SUMIF(Data!$L$2:$L$1001,E14,Data!$W$2:$W$1001) | G14: =SUMIF(Data!$L$2:$L$1001,E14,Data!$X$2:$X$1001) | I14: West | J14: =SUMIF(Data!$O$2:$O$1001,I14,Data!$W$2:$W$1001) | K14: =SUMIF(Data!$O$2:$O$1001,I14,Data!$X$2:$X$1001)
A15: Sep-23 | B15: =SUMIF(Data!$G$2:$G$1001,A15,Data!$W$2:$W$1001) | C15: =SUMIF(Data!$G$2:$G$1001,A15,Data!$X$2:$X$1001) | E15: Stationery | F15: =SUMIF(Data!$L$2:$L$1001,E15,Data!$W$2:$W$1001) | G15: =SUMIF(Data!$L$2:$L$1001,E15,Data!$X$2:$X$1001)
A16: Oct-23 | B16: =SUMIF(Data!$G$2:$G$1001,A16,Data!$W$2:$W$1001) | C16: =SUMIF(Data!$G$2:$G$1001,A16,Data!$X$2:$X$1001)
A17: Nov-23 | B17: =SUMIF(Data!$G$2:$G$1001,A17,Data!$W$2:$W$1001) | C17: =SUMIF(Data!$G$2:$G$1001,A17,Data!$X$2:$X$1001)
A18: Dec-23 | B18: =SUMIF(Data!$G$2:$G$1001,A18,Data!$W$2:$W$1001) | C18: =SUMIF(Data!$G$2:$G$1001,A18,Data!$X$2:$X$1001)
A19: Jan-24 | B19: =SUMIF(Data!$G$2:$G$1001,A19,Data!$W$2:$W$1001) | C19: =SUMIF(Data!$G$2:$G$1001,A19,Data!$X$2:$X$1001)
A20: Feb-24 | B20: =SUMIF(Data!$G$2:$G$1001,A20,Data!$W$2:$W$1001) | C20: =SUMIF(Data!$G$2:$G$1001,A20,Data!$X$2:$X$1001)
A21: Mar-24 | B21: =SUMIF(Data!$G$2:$G$1001,A21,Data!$W$2:$W$1001) | C21: =SUMIF(Data!$G$2:$G$1001,A21,Data!$X$2:$X$1001)
A22: Apr-24 | B22: =SUMIF(Data!$G$2:$G$1001,A22,Data!$W$2:$W$1001) | C22: =SUMIF(Data!$G$2:$G$1001,A22,Data!$X$2:$X$1001)
A23: May-24 | B23: =SUMIF(Data!$G$2:$G$1001,A23,Data!$W$2:$W$1001) | C23: =SUMIF(Data!$G$2:$G$1001,A23,Data!$X$2:$X$1001)
A24: Jun-24 | B24: =SUMIF(Data!$G$2:$G$1001,A24,Data!$W$2:$W$1001) | C24: =SUMIF(Data!$G$2:$G$1001,A24,Data!$X$2:$X$1001)
A25: Jul-24 | B25: =SUMIF(Data!$G$2:$G$1001,A25,Data!$W$2:$W$1001) | C25: =SUMIF(Data!$G$2:$G$1001,A25,Data!$X$2:$X$1001)
A26: Aug-24 | B26: =SUMIF(Data!$G$2:$G$1001,A26,Data!$W$2:$W$1001) | C26: =SUMIF(Data!$G$2:$G$1001,A26,Data!$X$2:$X$1001)
A27: Sep-24 | B27: =SUMIF(Data!$G$2:$G$1001,A27,Data!$W$2:$W$1001) | C27: =SUMIF(Data!$G$2:$G$1001,A27,Data!$X$2:$X$1001)
... A34: Apr-25 | B34: =SUMIF(Data!$G$2:$G$1001,A34,Data!$W$2:$W$1001) | C34: =SUMIF(Data!$G$2:$G$1001,A34,Data!$X$2:$X$1001)

Sheet Data
A1: Order ID | B1: Order Date | C1: Year | D1: Quarter | E1: Month | F1: Month No | G1: Month-Year | H1: Customer ID | I1: Customer Name | J1: Product ID | K1: Product Name | L1: Category | M1: Sub Category | N1: Brand | O1: Region | P1: State | Q1: City | R1: Sales Person | S1: Quantity | T1: Unit Price | U1: Discount % | V1: Cost Price | W1: Sales | X1: Profit | Y1: Profit Margin % | Z1: Gross Profit | AA1: Net Profit | AB1: Order Status | AC1: Payment Mode | AD1: Ship Mode | AE1: Return Status
A2: ORD00001 | B2: 45518 | C2: 2024 | D2: Q3 | E2: August | F2: 8 | G2: Aug-24 | H2: C230 | I2: Rahul | J2: P001 | K2: Apple Laptop | L2: Electronics | M2: Laptop | N2: Apple | O2: Central | P2: Illinois | Q2: Chicago | R2: Divya | S2: 5 | T2: 725.73 | U2: 5 | V2: 532.36 | W2: 3447.22 | X2: 785.42 | Y2: 22.78 | Z2: 785.42 | AA2: 785.42 | AB2: Shipped | AC2: UPI | AD2: Express | AE2: No
A3: ORD00002 | B3: 45132 | C3: 2023 | D3: Q3 | E3: July | F3: 7 | G3: Jul-23 | H3: C438 | I3: Vivaan | J3: P002 | K3: Dell Laptop | L3: Electronics | M3: Laptop | N3: Dell | O3: North | P3: New York | Q3: New York | R3: Arjun | S3: 6 | T3: 1319.56 | U3: 15 | V3: 671.4 | W3: 6729.76 | X3: 2701.36 | Y3: 40.14 | Z3: 2701.36 | AA3: 2701.36 | AB3: Shipped | AC3: Credit Card | AD3: Express | AE3: No
A4: ORD00003 | B4: 45167 | C4: 2023 | D4: Q3 | E4: August | F4: 8 | G4: Aug-23 | H4: C040 | I4: Ganesh | J4: P001 | K4: Apple Laptop | L4: Electronics | M4: Laptop | N4: Apple | O4: North | P4: New York | Q4: New York | R4: Shreya | S4: 8 | T4: 988.45 | U4: 15 | V4: 644.89 | W4: 6721.46 | X4: 1562.34 | Y4: 23.24 | Z4: 1562.34 | AA4: 1562.34 | AB4: Completed | AC4: Credit Card | AD4: Express | AE4: No
A5: ORD00004 | B5: 45317 | C5: 2024 | D5: Q1 | E5: January | F5: 1 | G5: Jan-24 | H5: C045 | I5: Deepak | J5: P012 | K5: HP Mouse | L5: Accessories | M5: Mouse | N5: HP | O5: Central | P5: Illinois | Q5: Chicago | R5: Sanjay | S5: 5 | T5: 207.98 | U5: 15 | V5: 165.27 | W5: 883.91 | X5: 57.56 | Y5: 6.51 | Z5: 57.56 | AA5: 57.56 | AB5: Pending | AC5: Credit Card | AD5: Standard | AE5: No
A6: ORD00005 | B6: 45294 | C6: 2024 | D6: Q1 | E6: January | F6: 1 | G6: Jan-24 | H6: C271 | I6: Pooja | J6: P018 | K6: HP Notebook | L6: Stationery | M6: Notebook | N6: HP | O6: North | P6: New York | Q6: New York | R6: Kavya | S6: 2 | T6: 331.4 | U6: 5 | V6: 170.48 | W6: 629.66 | X6: 288.7 | Y6: 45.85 | Z6: 288.7 | AA6: 288.7 | AB6: Completed | AC6: Credit Card | AD6: Standard | AE6: No
A7: ORD00006 | B7: 45390 | C7: 2024 | D7: Q2 | E7: April | F7: 4 | G7: Apr-24 | H7: C413 | I7: Manoj | J7: P003 | K7: HP Laptop | L7: Electronics | M7: Laptop | N7: HP | O7: South | P7: Florida | Q7: Miami | R7: Raj | S7: 3 | T7: 1015.93 | U7: 10 | V7: 682.84 | W7: 2743.01 | X7: 694.49 | Y7: 25.32 | Z7: 694.49 | AA7: 694.49 | AB7: Pending | AC7: UPI | AD7: Standard | AE7: Yes
A8: ORD00007 | B8: 45764 | C8: 2025 | D8: Q2 | E8: April | F8: 4 | G8: Apr-25 | H8: C032 | I8: Mahesh | J8: P007 | K8: Apple Desk | L8: Furniture | M8: Desk | N8: Apple | O8: South | P8: Florida | Q8: Miami | R8: Arjun | S8: 8 | T8: 79.22 | U8: 5 | V8: 55.12 | W8: 602.07 | X8: 161.11 | Y8: 26.76 | Z8: 161.11 | AA8: 161.11 | AB8: Completed | AC8: UPI | AD8: Express | AE8: Yes
A9: ORD00008 | B9: 45628 | C9: 2024 | D9: Q4 | E9: December | F9: 12 | G9: Dec-24 | H9: C409 | I9: Manoj | J9: P015 | K9: HP Blender | L9: Appliances | M9: Blender | N9: HP | O9: Central | P9: Illinois | Q9: Chicago | R9: Rohan | S9: 7 | T9: 472.17 | U9: 10 | V9: 318.29 | W9: 2974.67 | X9: 746.64 | Y9: 25.1 | Z9: 746.64 | AA9: 746.64 | AB9: Shipped | AC9: Credit Card | AD9: Express | AE9: Yes
A10: ORD00009 | B10: 45292 | C10: 2024 | D10: Q1 | E10: January | F10: 1 | G10: Jan-24 | H10: C362 | I10: Riya | J10: P012 | K10: HP Mouse | L10: Accessories | M10: Mouse | N10: HP | O10: South | P10: Texas | Q10: Dallas | R10: Pallavi | S10: 2 | T10: 1050.13 | U10: 15 | V10: 787.3 | W10: 1785.22 | X10: 210.62 | Y10: 11.8 | Z10: 210.62 | AA10: 210.62 | AB10: Shipped | AC10: Cash | AD10: Standard | AE10: Yes
A11: ORD00010 | B11: 45684 | C11: 2025 | D11: Q1 | E11: January | F11: 1 | G11: Jan-25 | H11: C267 | I11: Aditya | J11: P014 | K11: Dell Blender | L11: Appliances | M11: Blender | N11: Dell | O11: South | P11: Florida | Q11: Miami | R11: Vikas | S11: 3 | T11: 131.79 | U11: 5 | V11: 79.93 | W11: 375.6 | X11: 135.81 | Y11: 36.16 | Z11: 135.81 | AA11: 135.81 | AB11: Shipped | AC11: Credit Card | AD11: Express | AE11: Yes
A12: ORD00011 | B12: 45686 | C12: 2025 | D12: Q1 | E12: January | F12: 1 | G12: Jan-25 | H12: C020 | I12: Prakash | J12: P006 | K12: HP Monitor | L12: Electronics | M12: Monitor | N12: HP | O12: West | P12: Washington | Q12: Seattle | R12: Suresh | S12: 2 | T12: 386.56 | U12: 10 | V12: 193.95 | W12: 695.81 | X12: 307.91 | Y12: 44.25 | Z12: 307.91 | AA12: 307.91 | AB12: Pending | AC12: UPI | AD12: Express | AE12: Yes
A13: ORD00012 | B13: 45480 | C13: 2024 | D13: Q3 | E13: July | F13: 7 | G13: Jul-24 | H13: C237 | I13: Meera | J13: P002 | K13: Dell Laptop | L13: Electronics | M13: Laptop | N13: Dell | O13: Central | P13: Illinois | Q13: Chicago | R13: Meera | S13: 2 | T13: 1253.5 | U13: 10 | V13: 652.91 | W13: 2256.3 | X13: 950.48 | Y13: 42.13 | Z13: 950.48 | AA13: 950.48 | AB13: Completed | AC13: Credit Card | AD13: Standard | AE13: Yes
... A501: ORD00500 | B501: 45550 | C501: 2024 | D501: Q3 | E501: September | F501: 9 | G501: Sep-24 | H501: C269 | I501: Deepak | J501: P007 | K501: Apple Desk | L501: Furniture | M501: Desk | N501: Apple | O501: Central | P501: Illinois | Q501: Chicago | R501: Arun | S501: 5 | T501: 1381.95 | U501: 5 | V501: 1038.34 | W501: 6564.26 | X501: 1372.56 | Y501: 20.91 | Z501: 1372.56 | AA501: 1372.56 | AB501: Pending | AC501: Credit Card | AD501: Express | AE501: Yes
